agentc_llamaindex/__init__.py
agentc_llamaindex/chat/__init__.py
agentc_llamaindex/chat/chat.py
agentc_llamaindex-0.2.5a2.dist-info/METADATA
agentc_llamaindex-0.2.5a2.dist-info/WHEEL
agentc_llamaindex-0.2.5a2.dist-info/RECORD
